clovers_sarof/modules/ranklist/__init__.py
clovers_sarof/modules/ranklist/image.py
clovers_sarof/modules/ranklist/rankdata.py
clovers_sarof_ranklist-0.1.0.dist-info/METADATA
clovers_sarof_ranklist-0.1.0.dist-info/WHEEL
clovers_sarof_ranklist-0.1.0.dist-info/RECORD
